[
  {"Ciudad": "Pasto", "Departamento": "Nariño", "CodigoDIAN": "52001"},
  {"Ciudad": "Albán", "Departamento": "Nariño", "CodigoDIAN": "52019"},
  {"Ciudad": "Aldana", "Departamento": "Nariño", "CodigoDIAN": "52022"},
  {"Ciudad": "Ancuyá", "Departamento": "Nariño", "CodigoDIAN": "52036"},
  {"Ciudad": "Arboleda", "Departamento": "Nariño", "CodigoDIAN": "52051"},
  {"Ciudad": "Barbacoas", "Departamento": "Nariño", "CodigoDIAN": "52079"},
  {"Ciudad": "Belén", "Departamento": "Nariño", "CodigoDIAN": "52083"},
  {"Ciudad": "Buesaco", "Departamento": "Nariño", "CodigoDIAN": "52110"},
  {"Ciudad": "Colón", "Departamento": "Nariño", "CodigoDIAN": "52203"},
  {"Ciudad": "Consaca", "Departamento": "Nariño", "CodigoDIAN": "52207"},
  {"Ciudad": "Contadero", "Departamento": "Nariño", "CodigoDIAN": "52210"},
  {"Ciudad": "Córdoba", "Departamento": "Nariño", "CodigoDIAN": "52215"},
  {"Ciudad": "Cuaspud", "Departamento": "Nariño", "CodigoDIAN": "52224"},
  {"Ciudad": "Cumbal", "Departamento": "Nariño", "CodigoDIAN": "52227"},
  {"Ciudad": "Cumbitara", "Departamento": "Nariño", "CodigoDIAN": "52233"},
  {"Ciudad": "Chachagüí", "Departamento": "Nariño", "CodigoDIAN": "52240"},
  {"Ciudad": "El Charco", "Departamento": "Nariño", "CodigoDIAN": "52250"},
  {"Ciudad": "El Peñol", "Departamento": "Nariño", "CodigoDIAN": "52254"},
  {"Ciudad": "El Rosario", "Departamento": "Nariño", "CodigoDIAN": "52256"},
  {"Ciudad": "El Tablón De Gómez", "Departamento": "Nariño", "CodigoDIAN": "52258"},
  {"Ciudad": "El Tambo", "Departamento": "Nariño", "CodigoDIAN": "52260"},
  {"Ciudad": "Funes", "Departamento": "Nariño", "CodigoDIAN": "52287"},
  {"Ciudad": "Guachucal", "Departamento": "Nariño", "CodigoDIAN": "52317"},
  {"Ciudad": "Guaitarilla", "Departamento": "Nariño", "CodigoDIAN": "52320"},
  {"Ciudad": "Gualmatán", "Departamento": "Nariño", "CodigoDIAN": "52323"},
  {"Ciudad": "Iles", "Departamento": "Nariño", "CodigoDIAN": "52352"},
  {"Ciudad": "Imués", "Departamento": "Nariño", "CodigoDIAN": "52354"},
  {"Ciudad": "Ipiales", "Departamento": "Nariño", "CodigoDIAN": "52356"},
  {"Ciudad": "La Cruz", "Departamento": "Nariño", "CodigoDIAN": "52378"},
  {"Ciudad": "La Florida", "Departamento": "Nariño", "CodigoDIAN": "52381"},
  {"Ciudad": "La Llanada", "Departamento": "Nariño", "CodigoDIAN": "52385"},
  {"Ciudad": "La Tola", "Departamento": "Nariño", "CodigoDIAN": "52390"},
  {"Ciudad": "La Unión", "Departamento": "Nariño", "CodigoDIAN": "52399"},
  {"Ciudad": "Leiva", "Departamento": "Nariño", "CodigoDIAN": "52405"},
  {"Ciudad": "Linares", "Departamento": "Nariño", "CodigoDIAN": "52411"},
  {"Ciudad": "Los Andes", "Departamento": "Nariño", "CodigoDIAN": "52418"},
  {"Ciudad": "Magüi", "Departamento": "Nariño", "CodigoDIAN": "52427"},
  {"Ciudad": "Mallama", "Departamento": "Nariño", "CodigoDIAN": "52435"},
  {"Ciudad": "Mosquera", "Departamento": "Nariño", "CodigoDIAN": "52473"},
  {"Ciudad": "Nariño", "Departamento": "Nariño", "CodigoDIAN": "52480"},
  {"Ciudad": "Olaya Herrera", "Departamento": "Nariño", "CodigoDIAN": "52490"},
  {"Ciudad": "Ospina", "Departamento": "Nariño", "CodigoDIAN": "52506"},
  {"Ciudad": "Francisco Pizarro", "Departamento": "Nariño", "CodigoDIAN": "52520"},
  {"Ciudad": "Policarpa", "Departamento": "Nariño", "CodigoDIAN": "52540"},
  {"Ciudad": "Potosí", "Departamento": "Nariño", "CodigoDIAN": "52560"},
  {"Ciudad": "Providencia", "Departamento": "Nariño", "CodigoDIAN": "52565"},
  {"Ciudad": "Puerres", "Departamento": "Nariño", "CodigoDIAN": "52573"},
  {"Ciudad": "Pupiales", "Departamento": "Nariño", "CodigoDIAN": "52585"},
  {"Ciudad": "Ricaurte", "Departamento": "Nariño", "CodigoDIAN": "52612"},
  {"Ciudad": "Roberto Payán", "Departamento": "Nariño", "CodigoDIAN": "52621"},
  {"Ciudad": "Samaniego", "Departamento": "Nariño", "CodigoDIAN": "52678"},
  {"Ciudad": "Sandoná", "Departamento": "Nariño", "CodigoDIAN": "52683"},
  {"Ciudad": "San Bernardo", "Departamento": "Nariño", "CodigoDIAN": "52685"},
  {"Ciudad": "San Lorenzo", "Departamento": "Nariño", "CodigoDIAN": "52687"},
  {"Ciudad": "San Pablo", "Departamento": "Nariño", "CodigoDIAN": "52693"},
  {"Ciudad": "San Pedro De Cartago", "Departamento": "Nariño", "CodigoDIAN": "52694"},
  {"Ciudad": "Santa Bárbara", "Departamento": "Nariño", "CodigoDIAN": "52696"},
  {"Ciudad": "Santacruz", "Departamento": "Nariño", "CodigoDIAN": "52699"},
  {"Ciudad": "Sapuyes", "Departamento": "Nariño", "CodigoDIAN": "52720"},
  {"Ciudad": "Taminango", "Departamento": "Nariño", "CodigoDIAN": "52786"},
  {"Ciudad": "Tangua", "Departamento": "Nariño", "CodigoDIAN": "52788"},
  {"Ciudad": "San Andres De Tumaco", "Departamento": "Nariño", "CodigoDIAN": "52835"},
  {"Ciudad": "Túquerres", "Departamento": "Nariño", "CodigoDIAN": "52838"},
  {"Ciudad": "Yacuanquer", "Departamento": "Nariño", "CodigoDIAN": "52885"}
]
